README.txt
setup.py
collective/__init__.py
collective.blueprint.translationlinker.egg-info/PKG-INFO
collective.blueprint.translationlinker.egg-info/SOURCES.txt
collective.blueprint.translationlinker.egg-info/dependency_links.txt
collective.blueprint.translationlinker.egg-info/namespace_packages.txt
collective.blueprint.translationlinker.egg-info/not-zip-safe
collective.blueprint.translationlinker.egg-info/requires.txt
collective.blueprint.translationlinker.egg-info/top_level.txt
collective/blueprint/__init__.py
collective/blueprint/translationlinker/__init__.py
collective/blueprint/translationlinker/configure.zcml
docs/HISTORY.txt
docs/LICENSE.GPL
docs/LICENSE.txt