Metadata-Version: 1.0
Name: collective.blueprint.translationlinker
Version: 1.0.1
Summary: UNKNOWN
Home-page: http://svn.plone.org/svn/collective/collective.blueprint.translationlinker
Author: Florian Schulze
Author-email: florian.schulze@gmx.net
License: GPL
Platform: UNKNOWN
Classifier: Framework :: Plone
Classifier: Programming Language :: Python
Classifier: Topic :: Software Development :: Libraries :: Python Modules
